systeme_solaire/app.py
systeme_solaire-0.1.0.dist-info/METADATA
systeme_solaire-0.1.0.dist-info/WHEEL
systeme_solaire-0.1.0.dist-info/RECORD
