Metadata-Version: 2.1
Name: systeme-solaire
Version: 0.1.0
Summary: Application de représentation du système solaire
License: MIT
Author: Jules RENIER
Requires-Python: >=3.9,<4.0
Classifier: License :: OSI Approved :: MIT License
Classifier: Programming Language :: Python :: 3
Classifier: Programming Language :: Python :: 3.9
Classifier: Programming Language :: Python :: 3.10
Classifier: Programming Language :: Python :: 3.11
Requires-Dist: astroquery (>=0.4.6,<0.5.0)
